filler_pdf/__init__.py
filler_pdf/pdffiller.py
filler_pdf-0.2.dist-info/METADATA
filler_pdf-0.2.dist-info/WHEEL
filler_pdf-0.2.dist-info/top_level.txt
filler_pdf-0.2.dist-info/RECORD
