Metadata-Version: 2.1
Name: filler_pdf
Version: 0.2
Author: Mayur Talreja
Author-email: talrejamayur6@gmail.com
